django_qrcode_filter
