Metadata-Version: 1.0
Name: django-qrcode-filter
Version: 0.0.9alpha
Summary: A simplet django application that provides a block and fitler templatetag to create inline DataURI based qrcode images.
Home-page: projects.airtonix.net/project/django-qrcode-filter
Author: Zenobius Jiricek
Author-email: airtonix@gmail.com
License: LICENSE.md
Platform: UNKNOWN
